di_linter/__init__.py
di_linter/cli.py
di_linter/common.py
di_linter/flake8_plugin.py
di_linter/graph.py
di_linter/main.py
di_linter/patch_linter.py
di_linter/search_modules.py
di_linter/utils.py
di_linter-1.3.0.dist-info/METADATA
di_linter-1.3.0.dist-info/WHEEL
di_linter-1.3.0.dist-info/entry_points.txt
di_linter-1.3.0.dist-info/licenses/LICENSE
di_linter-1.3.0.dist-info/RECORD
