Metadata-Version: 2.4
Name: di-linter
Version: 1.3.0
Summary: Static code analysis for search of dependencies injection
Project-URL: Homepage, https://github.com/pavelmaksimov/di-linter
Project-URL: Bug Tracker, https://github.com/pavelmaksimov/di-linter/issues
Author-email: Pavel Maksimov <vur21@yandex.ru>
License-File: LICENSE
Requires-Python: >=3.11
Provides-Extra: flake8
Requires-Dist: flake8>=7.2.0; extra == 'flake8'
